{
  "BabyNames":
  [
    {"Name":"Olivia","Type":"Feminine","Origin":"Latin","Meaning":"Olive tree","Website":"https://www.thebump.com/b/olivia-baby-name"},
    {"Name":"Charlotte","Type":"Feminine","Origin":"French","Meaning":"Free man","Website":"https://www.thebump.com/b/charlotte-baby-name"},
    {"Name":"Ava","Type":"Feminine","Origin":"Latin","Meaning":"Bird, life","Website":"https://www.thebump.com/b/ava-baby-name"},
    {"Name":"Evelyn","Type":"Feminine","Origin":"British","Meaning":"Desired","Website":"https://www.thebump.com/b/evelyn-baby-name"},
    {"Name":"Victoria","Type":"Feminine","Origin":"Latin","Meaning":"Victory","Website":"https://www.thebump.com/b/victoria-baby-name"},
    {"Name":"Nathan","Type":"Masculine","Origin":"Hebrew","Meaning":"To give","Website":"https://www.thebump.com/b/nathan-baby-name"},
    {"Name":"Lucas","Type":"Masculine","Origin":"Latin","Meaning":"Bringer of light","Website":"https://www.thebump.com/b/lucas-baby-name"},
    {"Name":"Henry","Type":"Masculine","Origin":"German","Meaning":"House ruler","Website":"https://www.thebump.com/b/henry-baby-name"},
    {"Name":"Theodore","Type":"Masculine","Origin":"Greek","Meaning":"God's gift","Website":"https://www.thebump.com/b/theodore-baby-name"},
    {"Name":"Felix","Type":"Masculine","Origin":"Latin","Meaning":"Happy","Website":"https://www.thebump.com/b/felix-baby-name"},
    {"Name":"Logan","Type":"Unisex","Origin":"Scottish","Meaning":"Hollow","Website":"https://www.thebump.com/b/logan-baby-name"},
    {"Name":"Dakota","Type":"Unisex","Origin":"Native American","Meaning":"Friend","Website":"https://www.thebump.com/b/dakota-baby-name"},
    {"Name":"Emerson","Type":"Unisex","Origin":"German","Meaning":"Brave","Website":"https://www.thebump.com/b/emerson-baby-name"},
    {"Name":"Kai","Type":"Unisex","Origin":"Welsh","Meaning":"Earth","Website":"https://www.thebump.com/b/kai-baby-name"},
    {"Name":"Blake","Type":"Unisex","Origin":"British","Meaning":"Bright","Website":"https://www.thebump.com/b/blake-baby-name"},
  ],
  "Status":"OK"
}
